setup.cfg
setup.py
angemilner/__init__.py
angemilner/key_librarian.py
angemilner.egg-info/PKG-INFO
angemilner.egg-info/SOURCES.txt
angemilner.egg-info/dependency_links.txt
angemilner.egg-info/entry_points.txt
angemilner.egg-info/requires.txt
angemilner.egg-info/top_level.txt
angemilner.egg-info/zip-safe