Metadata-Version: 1.1
Name: angemilner
Version: 0.2.01-r0
Summary: Manages a library of API keys using MongoDB to prevent rate limiting
Home-page: https://github.com/rawkintrevo/API-Key-Librarian
Author: Trevor Grant
Author-email: trevor.d.grant@gmail.com
License: Apache License v2.0
Platform: UNKNOWN
Classifier: Development Status :: 5 - Production/Stable
Classifier: License :: OSI Approved :: Apache Software License
